breadcrumbs/__init__.py
breadcrumbs/namedobject.py
breadcrumbs/testsuite/__init__.py
breadcrumbs/testsuite/test_all.py
use_breadcrumbs-0.2.dist-info/AUTHORS
use_breadcrumbs-0.2.dist-info/LICENSE
use_breadcrumbs-0.2.dist-info/METADATA
use_breadcrumbs-0.2.dist-info/WHEEL
use_breadcrumbs-0.2.dist-info/top_level.txt
use_breadcrumbs-0.2.dist-info/zip-safe
use_breadcrumbs-0.2.dist-info/RECORD
